{"cameraMode":{"drawMode":0,"name":"Shaded","section":"Shading Mode"},"sceneLighting":true,"audioPlay":false,"sceneViewState":{"m_AlwaysRefresh":false,"showFog":true,"showSkybox":true,"showFlares":true,"showImageEffects":true,"showParticleSystems":true,"showVisualEffectGraphs":true,"m_FxEnabled":true},"in2DMode":false,"pivot":{"x":-2.623584508895874,"y":13.485594749450684,"z":4.547672271728516},"rotation":{"x":0.21605756878852845,"y":-0.21755748987197877,"z":0.0494503416121006,"w":0.950550377368927},"size":12.789257049560547,"orthographic":false}